llm_core/__init__.py
llm_core/loaders.py
llm_core/parsers.py
llm_core/schema.py
llm_core/settings.py
llm_core/splitters.py
llm_core/tokenizers.py
llm_core/assistants/__init__.py
llm_core/assistants/base.py
llm_core/llm/__init__.py
llm_core/llm/anthropic.py
llm_core/llm/base.py
llm_core/llm/google.py
llm_core/llm/mistralai.py
llm_core/llm/open_weights.py
llm_core/llm/openai.py
py_llm_core-3.5.0.dist-info/LICENSE
py_llm_core-3.5.0.dist-info/METADATA
py_llm_core-3.5.0.dist-info/WHEEL
py_llm_core-3.5.0.dist-info/top_level.txt
py_llm_core-3.5.0.dist-info/RECORD
