Metadata-Version: 2.1
Name: py-llm-core
Version: 3.5.0
Summary: PyLLMCore provides a light-weighted interface with LLMs
Home-page: https://github.com/paschembri/py-llm-core
Author: P.A. SCHEMBRI
Author-email: pa.schembri@advanced-stack.com
License: MIT
License-File: LICENSE
Requires-Dist: openai >=1.37
Requires-Dist: tiktoken
Requires-Dist: dirtyjson
Requires-Dist: llama-cpp-python >=0.2.84
Requires-Dist: python-decouple
Requires-Dist: mistralai
Requires-Dist: anthropic
Requires-Dist: Pillow
